MANIFEST.in
README.rst
setup.py
autoroot/__init__.py
autoroot/management/__init__.py
django_autoroot.egg-info/PKG-INFO
django_autoroot.egg-info/SOURCES.txt
django_autoroot.egg-info/dependency_links.txt
django_autoroot.egg-info/top_level.txt