Metadata-Version: 1.1
Name: django-autoroot
Version: 0.2.1
Summary: automaticly creates `root` user after syncdb if not exists
Home-page: http://github.com/spinus/django-autoroot
Author: Tomek Czyż
Author-email: tomekczyz@gmail.com
License: BSD
Keywords: django user create syncdb
Platform: OS Independent
Classifier: Environment :: Web Environment
Classifier: Framework :: Django
Classifier: Intended Audience :: Developers
Classifier: License :: OSI Approved :: BSD License
Classifier: Operating System :: OS Independent
Classifier: Programming Language :: Python
Classifier: Topic :: Internet :: WWW/HTTP :: Dynamic Content
Classifier: Topic :: Software Development :: Libraries :: Python Modules
